prediction_model/VERSION
prediction_model/__init__.py
prediction_model/config.yml
prediction_model/core.py
prediction_model/data_manager.py
prediction_model/features.py
prediction_model/pipeline.py
prediction_model/predict.py
prediction_model/train_pipeline.py
prediction_model/validation.py
prediction_model/datasets/Admission_Predict.csv
prediction_model/tests/__init__.py
prediction_model/tests/conftest.py
prediction_model/tests/test_features.py
prediction_model/tests/test_predict.py
prediction_model/trained_models/admission_model_output_v0.0.7.pkl
admission_prediction_model-0.0.7.dist-info/LICENSE
admission_prediction_model-0.0.7.dist-info/METADATA
admission_prediction_model-0.0.7.dist-info/WHEEL
admission_prediction_model-0.0.7.dist-info/top_level.txt
admission_prediction_model-0.0.7.dist-info/RECORD
